mcposprint/__init__.py
mcposprint/server.py
mcposprint/core/__init__.py
mcposprint/core/config.py
mcposprint/core/printer.py
mcposprint/generators/__init__.py
mcposprint/generators/card.py
mcposprint/parsers/__init__.py
mcposprint/parsers/markdown.py
mcposprint/parsers/notion.py
mcposprint/printers/__init__.py
mcposprint/printers/escpos_printer.py
mcposprint-1.0.0.dist-info/METADATA
mcposprint-1.0.0.dist-info/WHEEL
mcposprint-1.0.0.dist-info/entry_points.txt
mcposprint-1.0.0.dist-info/licenses/LICENSE
mcposprint-1.0.0.dist-info/RECORD
