Metadata-Version: 2.4
Name: mcposprint
Version: 1.0.0
Summary: MCP server for thermal printer task card generation
Project-URL: Homepage, https://github.com/bhandzo/mcposprint
Project-URL: Repository, https://github.com/bhandzo/mcposprint
Project-URL: Issues, https://github.com/bhandzo/mcposprint/issues
Project-URL: Documentation, https://github.com/bhandzo/mcposprint#readme
Author: MCPOSprint Contributors
License: MIT
License-File: LICENSE
Keywords: cards,escpos,mcp,printer,server,task,thermal,usb
Classifier: Development Status :: 5 - Production/Stable
Classifier: Intended Audience :: Developers
Classifier: License :: OSI Approved :: MIT License
Classifier: Operating System :: OS Independent
Classifier: Programming Language :: Python :: 3
Classifier: Programming Language :: Python :: 3.10
Classifier: Programming Language :: Python :: 3.11
Classifier: Programming Language :: Python :: 3.12
Classifier: Programming Language :: Python :: 3.13
Classifier: Topic :: Printing
Classifier: Topic :: Software Development :: Libraries
Classifier: Topic :: System :: Hardware :: Hardware Drivers
Requires-Python: >=3.10
Requires-Dist: mcp[cli]>=1.10.1
Requires-Dist: pillow>=10.0.0
Requires-Dist: python-dotenv>=1.0.0
Requires-Dist: python-escpos>=3.0.0
Requires-Dist: pyusb>=1.3.1
Requires-Dist: qrcode[pil]>=7.4.0
Requires-Dist: requests>=2.31.0
Provides-Extra: dev
Requires-Dist: black>=23.0.0; extra == 'dev'
Requires-Dist: flake8>=6.0.0; extra == 'dev'
Requires-Dist: mypy>=1.0.0; extra == 'dev'
Requires-Dist: pytest-cov>=4.0.0; extra == 'dev'
Requires-Dist: pytest>=7.0.0; extra == 'dev'
